halo_mcp_server/__init__.py
halo_mcp_server/__main__.py
halo_mcp_server/_version.py
halo_mcp_server/client.py
halo_mcp_server/config.py
halo_mcp_server/exceptions.py
halo_mcp_server/server.py
halo_mcp_server/client/__init__.py
halo_mcp_server/client/base.py
halo_mcp_server/client/halo_client.py
halo_mcp_server/models/__init__.py
halo_mcp_server/models/common.py
halo_mcp_server/prompts/__init__.py
halo_mcp_server/prompts/blog_prompts.py
halo_mcp_server/tools/__init__.py
halo_mcp_server/tools/attachment_tools.py
halo_mcp_server/tools/category_tools.py
halo_mcp_server/tools/post_tools.py
halo_mcp_server/tools/site_tools.py
halo_mcp_server/tools/tag_tools.py
halo_mcp_server/utils/__init__.py
halo_mcp_server/utils/logger.py
halo_mcp_server-0.1.5.dist-info/licenses/LICENSE
halo_mcp_server-0.1.5.dist-info/METADATA
halo_mcp_server-0.1.5.dist-info/WHEEL
halo_mcp_server-0.1.5.dist-info/top_level.txt
halo_mcp_server-0.1.5.dist-info/RECORD
