Metadata-Version: 2.4
Name: halo-mcp-server
Version: 0.1.5
Summary: MCP for Halo blog system - AI-powered content management
Author: Halo MCP Contributors
License: MIT
Project-URL: Homepage, https://github.com/Huangwh826/halo-mcp-server
Project-URL: Documentation, https://github.com/Huangwh826/halo-mcp-server
Project-URL: Repository, https://github.com/Huangwh826/halo-mcp-server
Project-URL: Issues, https://github.com/Huangwh826/halo-mcp-server/issues
Keywords: mcp,halo,blog,ai,claude,content-management
Classifier: Development Status :: 3 - Alpha
Classifier: Intended Audience :: Developers
Classifier: License :: OSI Approved :: MIT License
Classifier: Programming Language :: Python :: 3
Classifier: Programming Language :: Python :: 3.10
Classifier: Programming Language :: Python :: 3.11
Classifier: Programming Language :: Python :: 3.12
Classifier: Topic :: Software Development :: Libraries :: Python Modules
Classifier: Topic :: Internet :: WWW/HTTP :: Dynamic Content :: Content Management System
Requires-Python: >=3.10
License-File: LICENSE
Requires-Dist: mcp>=0.9.0
Requires-Dist: httpx>=0.25.0
Requires-Dist: pydantic>=2.0.0
Requires-Dist: pydantic-settings>=2.0.0
Requires-Dist: python-dotenv>=1.0.0
Requires-Dist: loguru>=0.7.0
Requires-Dist: aiofiles>=23.0.0
Requires-Dist: Pillow>=10.0.0
Requires-Dist: python-slugify>=8.0.0
Requires-Dist: markdown>=3.5.0
Requires-Dist: markdown-it-py>=4.0.0
Requires-Dist: mdit-py-plugins>=0.4.0
Requires-Dist: linkify-it-py>=2.0.0
Requires-Dist: mdit-py-toc>=0.1.0
Provides-Extra: dev
Requires-Dist: pytest>=7.4.0; extra == "dev"
Requires-Dist: pytest-asyncio>=0.21.0; extra == "dev"
Requires-Dist: pytest-cov>=4.1.0; extra == "dev"
Requires-Dist: pytest-mock>=3.12.0; extra == "dev"
Requires-Dist: black>=23.7.0; extra == "dev"
Requires-Dist: isort>=5.12.0; extra == "dev"
Requires-Dist: mypy>=1.5.0; extra == "dev"
Requires-Dist: ruff>=0.1.2; extra == "dev"
Requires-Dist: pre-commit>=3.3.0; extra == "dev"
Dynamic: license-file
